LICENSE
MANIFEST.in
README.md
setup.py
pyscheduler/__init__.py
pyscheduler/examples.py
python_scheduler.egg-info/PKG-INFO
python_scheduler.egg-info/SOURCES.txt
python_scheduler.egg-info/dependency_links.txt
python_scheduler.egg-info/requires.txt
python_scheduler.egg-info/top_level.txt