Metadata-Version: 1.1
Name: python-scheduler
Version: 0.0.1
Summary: Create scheduled tasks at runtime easily
Home-page: https://github.com/baranbartu/pyscheduler
Author: Baran Bartu Demirci
Author-email: bbartu.demirci@gmail.com
License: MIT
Download-URL: https://github.com/baranbartu/pyscheduler/tarball/0.0.1
Keywords: scheduler scheduled tasks crontab cron cronjob celery
Platform: UNKNOWN
